osu_stream_speed.py
osu_stream_speed-0.0.1.dist-info/LICENSE
osu_stream_speed-0.0.1.dist-info/METADATA
osu_stream_speed-0.0.1.dist-info/WHEEL
osu_stream_speed-0.0.1.dist-info/entry_points.txt
osu_stream_speed-0.0.1.dist-info/top_level.txt
osu_stream_speed-0.0.1.dist-info/RECORD
