Metadata-Version: 2.1
Name: osu-stream-speed
Version: 0.0.1
Summary: Test your osu! streaming speed.
Home-page: https://github.com/cmyui/osu-stream-speed
Author: Josh Smith
Author-email: josh@akatsuki.gg
License: MIT
Classifier: License :: OSI Approved :: MIT License
Classifier: Programming Language :: Python :: 3
Classifier: Programming Language :: Python :: 3 :: Only
Classifier: Programming Language :: Python :: Implementation :: CPython
Requires-Python: >=3.7
License-File: LICENSE
